odoo/addons/product_brand_purchase/README.rst
odoo/addons/product_brand_purchase/__init__.py
odoo/addons/product_brand_purchase/__manifest__.py
odoo/addons/product_brand_purchase/i18n/es.po
odoo/addons/product_brand_purchase/i18n/it.po
odoo/addons/product_brand_purchase/i18n/nl.po
odoo/addons/product_brand_purchase/i18n/product_brand_purchase.pot
odoo/addons/product_brand_purchase/readme/CONTRIBUTORS.md
odoo/addons/product_brand_purchase/readme/DESCRIPTION.md
odoo/addons/product_brand_purchase/readme/USAGE.md
odoo/addons/product_brand_purchase/reports/__init__.py
odoo/addons/product_brand_purchase/reports/purchase_report.py
odoo/addons/product_brand_purchase/reports/purchase_report_view.xml
odoo/addons/product_brand_purchase/static/description/icon.png
odoo/addons/product_brand_purchase/static/description/index.html
odoo/addons/product_brand_purchase/tests/__init__.py
odoo/addons/product_brand_purchase/tests/test_product_brand_purchase.py
odoo/addons/product_brand_purchase/views/product_brand_view.xml
odoo_addon_product_brand_purchase-18.0.1.0.0.4.dist-info/METADATA
odoo_addon_product_brand_purchase-18.0.1.0.0.4.dist-info/WHEEL
odoo_addon_product_brand_purchase-18.0.1.0.0.4.dist-info/top_level.txt
odoo_addon_product_brand_purchase-18.0.1.0.0.4.dist-info/RECORD
